zimage/__init__.py
zimage-0.1.1.dist-info/METADATA
zimage-0.1.1.dist-info/WHEEL
zimage-0.1.1.dist-info/licenses/LICENSE
zimage-0.1.1.dist-info/RECORD
