Metadata-Version: 2.1
Name: zimage
Version: 0.1.1
Summary: zen image library
Project-URL: Homepage, https://github.com/inspirare6/zimage
Project-URL: Bug Tracker, https://github.com/inspirare6/zimage/issues
Author-email: inspirare6 <inspirare6@163.com>
License-File: LICENSE
Classifier: License :: OSI Approved :: MIT License
Classifier: Operating System :: OS Independent
Classifier: Programming Language :: Python :: 3
Requires-Python: >=3.7
Requires-Dist: pillow
Requires-Dist: qrcode
